metaros/__init__.py
metaros/datalogger.py
metaros/message_broker.py
metaros/publisher.py
metaros/rate.py
metaros/subscriber.py
metaros/timer.py
metaros/topic.py
metaros/messages/__init__.py
metaros/messages/geometry_msgs.py
metaros/messages/nav_msgs.py
metaros/messages/sensor_msgs.py
metaros/messages/std_msgs.py
metaros-1.0.7.dist-info/LICENSE
metaros-1.0.7.dist-info/METADATA
metaros-1.0.7.dist-info/WHEEL
metaros-1.0.7.dist-info/top_level.txt
metaros-1.0.7.dist-info/RECORD
