Metadata-Version: 2.1
Name: metaros
Version: 1.0.7
Summary: Meta-ROS middleware
Home-page: https://github.com/AnshulRanjan2004/Meta-ROS
Author: Anshul Ranjan
Author-email: itsanshulranjan@gmail.com
Maintainer: Anshul Ranjan
Maintainer-email: itsanshulranjan@gmail.com
License: BSD-3-Clause
Project-URL: Bug Reports, https://github.com/AnshulRanjan2004/Meta-ROS/issues
Project-URL: Source, https://github.com/AnshulRanjan2004/Meta-ROS
Classifier: Development Status :: 4 - Beta
Classifier: Intended Audience :: Developers
Classifier: Intended Audience :: Science/Research
Classifier: License :: OSI Approved :: BSD License
Classifier: Programming Language :: Python :: 3
Classifier: Topic :: Software Development
Classifier: Topic :: Software Development :: Libraries
Classifier: Topic :: Software Development :: Libraries :: Python Modules
License-File: LICENSE
Requires-Dist: numpy >=1.23.4
Requires-Dist: pyzmq >=24.0.1
Requires-Dist: setuptools >=59.6.0
